ipa2unicode/__init__.py
ipa2unicode/ipa2unicode.py
ipa2unicode-1.0.dist-info/LICENSE
ipa2unicode-1.0.dist-info/LICENSE~
ipa2unicode-1.0.dist-info/METADATA
ipa2unicode-1.0.dist-info/WHEEL
ipa2unicode-1.0.dist-info/top_level.txt
ipa2unicode-1.0.dist-info/RECORD
