Metadata-Version: 2.1
Name: ipa2unicode
Version: 1.0
Summary: Package for converting SIL IPA93 legacy font to unicode
Home-page: http://pypi.python.org/pypi/ipa2unicode/
Author: Brooke Cowan
Author-email: cowanb@ohsu.edu
License: UNKNOWN
Platform: UNKNOWN
Classifier: Programming Language :: Python :: 3
Classifier: License :: OSI Approved :: MIT License
Classifier: Operating System :: OS Independent
